CHANGES.rst
MANIFEST.in
README.rst
setup.py
redistore/__init__.py
redistore/types.py
redistore.egg-info/PKG-INFO
redistore.egg-info/SOURCES.txt
redistore.egg-info/dependency_links.txt
redistore.egg-info/top_level.txt