Metadata-Version: 1.1
Name: redistore
Version: 0.1.0
Summary: Simple python interface for redis
Home-page: https://github.com/lamenezes/redistore
Author: Luiz Menezes
Author-email: luiz.menezesf@gmail.com
License: MIT
Platform: UNKNOWN
Classifier: Development Status :: 3 - Alpha
Classifier: Intended Audience :: Developers
Classifier: Programming Language :: Python :: 3
Classifier: Programming Language :: Python :: 3.5
